signalr/__init__.py
signalr/_connection.py
signalr/security.py
signalr/async_client/__init__.py
signalr/async_client/connection.py
signalr/events/__init__.py
signalr/events/_events.py
signalr/hubs/__init__.py
signalr/hubs/_hub.py
signalr/protocols/__init__.py
signalr/protocols/base.py
signalr/protocols/classic.py
signalr/protocols/core.py
signalr/transports/__init__.py
signalr/transports/_auto_transport.py
signalr/transports/_sse_transport.py
signalr/transports/_transport.py
signalr/transports/_ws_transport.py
signalr_unified_client-0.0.10.dist-info/licenses/AUTHORS
signalr_unified_client-0.0.10.dist-info/licenses/LICENSE.md
signalr_unified_client-0.0.10.dist-info/METADATA
signalr_unified_client-0.0.10.dist-info/WHEEL
signalr_unified_client-0.0.10.dist-info/top_level.txt
signalr_unified_client-0.0.10.dist-info/RECORD
