Metadata-Version: 2.4
Name: signalr-unified-client
Version: 0.0.10
Summary: Unified Python SignalR client: classic ASP.NET SignalR 2.x and ASP.NET Core SignalR
Home-page: https://github.com/your-org/signalr-unified-client
Author: Taucraft Limited, Michael Herrmann
Author-email: andy@datewood.net, Pawel Troka <pawel.troka@outlook.com>
License-Expression: Apache-2.0
Project-URL: Homepage, https://github.com/PawelTroka/signalr-client-threads
Project-URL: Repository, https://github.com/PawelTroka/signalr-client-threads
Keywords: signalr
Classifier: Development Status :: 3 - Alpha
Classifier: Intended Audience :: Developers
Classifier: Topic :: Software Development :: Libraries :: Python Modules
Classifier: Programming Language :: Python :: 3
Classifier: Programming Language :: Python :: 3 :: Only
Classifier: Programming Language :: Python :: 3.8
Classifier: Programming Language :: Python :: 3.9
Classifier: Programming Language :: Python :: 3.10
Classifier: Programming Language :: Python :: 3.11
Classifier: Programming Language :: Python :: 3.12
Classifier: Programming Language :: Python :: 3.13
Requires-Python: >=3.8
License-File: LICENSE.md
License-File: AUTHORS
Requires-Dist: websocket-client<2.0,>=1.8.0
Requires-Dist: sseclient-py<2.0,>=1.7
Requires-Dist: requests<3.0,>=2.32.0
Provides-Extra: async
Requires-Dist: websockets<14.0,>=12.0; extra == "async"
Requires-Dist: httpx<1.0,>=0.27.0; extra == "async"
Provides-Extra: core
Requires-Dist: websockets<14.0,>=12.0; extra == "core"
Provides-Extra: core-msgpack
Requires-Dist: msgpack<2.0,>=1.0.8; extra == "core-msgpack"
Provides-Extra: dev
Requires-Dist: pytest<9.0,>=8.0; extra == "dev"
Dynamic: home-page
Dynamic: license-file
